[
  {
    "image": "/instagram/post-2026-06-09-306503.jpg",
    "permalink": "https://www.instagram.com/p/DZWEJT8Df76/",
    "date": "2026-06-09",
    "type": "CAROUSEL_ALBUM",
    "captionExcerpt": "6 plans d’été à Montréal à sauver maintenant, à vivre dès juin."
  },
  {
    "image": "/instagram/post-2026-05-31-065775.jpg",
    "permalink": "https://www.instagram.com/p/DZBSF1slCxw/",
    "date": "2026-05-31",
    "type": "CAROUSEL_ALBUM",
    "captionExcerpt": "Mai à Montréal, version bubbleOut 🌞 "
  },
  {
    "image": "/instagram/post-2026-05-29-092071.jpg",
    "permalink": "https://www.instagram.com/p/DY8Ai_-BJ9P/",
    "date": "2026-05-29",
    "type": "IMAGE",
    "captionExcerpt": "Montréal le premier tournoi de Spike-Ball 2026 est là 🏐☀️ "
  },
  {
    "image": "/instagram/post-2026-05-26-087183.jpg",
    "permalink": "https://www.instagram.com/p/DYyCs41Db9L/",
    "date": "2026-05-26",
    "type": "CAROUSEL_ALBUM",
    "captionExcerpt": "Les apéros où les Montréalais•es se rencontrent 🫒"
  }
]
